{
 "fragments": [
  {
   "begin": "0.000", 
   "end": "0.200", 
   "id": "f000001", 
   "language": "en", 
   "lines": [
    "\ufeff\"Who"
   ]
  }, 
  {
   "begin": "0.200", 
   "end": "0.720", 
   "id": "f000002", 
   "language": "en", 
   "lines": [
    "are"
   ]
  }, 
  {
   "begin": "0.720", 
   "end": "1.120", 
   "id": "f000003", 
   "language": "en", 
   "lines": [
    "you?\""
   ]
  }, 
  {
   "begin": "1.120", 
   "end": "1.800", 
   "id": "f000004", 
   "language": "en", 
   "lines": [
    "a"
   ]
  }, 
  {
   "begin": "1.800", 
   "end": "2.200", 
   "id": "f000005", 
   "language": "en", 
   "lines": [
    "harsh"
   ]
  }, 
  {
   "begin": "2.200", 
   "end": "2.600", 
   "id": "f000006", 
   "language": "en", 
   "lines": [
    "voice"
   ]
  }, 
  {
   "begin": "2.600", 
   "end": "3.880", 
   "id": "f000007", 
   "language": "en", 
   "lines": [
    "demanded."
   ]
  }, 
  {
   "begin": "3.880", 
   "end": "4.160", 
   "id": "f000008", 
   "language": "en", 
   "lines": [
    "Mango"
   ]
  }, 
  {
   "begin": "4.160", 
   "end": "4.960", 
   "id": "f000009", 
   "language": "en", 
   "lines": [
    "realized"
   ]
  }, 
  {
   "begin": "4.960", 
   "end": "5.240", 
   "id": "f000010", 
   "language": "en", 
   "lines": [
    "he"
   ]
  }, 
  {
   "begin": "5.240", 
   "end": "5.520", 
   "id": "f000011", 
   "language": "en", 
   "lines": [
    "was"
   ]
  }, 
  {
   "begin": "5.520", 
   "end": "5.760", 
   "id": "f000012", 
   "language": "en", 
   "lines": [
    "in"
   ]
  }, 
  {
   "begin": "5.760", 
   "end": "5.840", 
   "id": "f000013", 
   "language": "en", 
   "lines": [
    "a"
   ]
  }, 
  {
   "begin": "5.840", 
   "end": "6.320", 
   "id": "f000014", 
   "language": "en", 
   "lines": [
    "protected"
   ]
  }, 
  {
   "begin": "6.320", 
   "end": "6.760", 
   "id": "f000015", 
   "language": "en", 
   "lines": [
    "Teak"
   ]
  }, 
  {
   "begin": "6.760", 
   "end": "8.240", 
   "id": "f000016", 
   "language": "en", 
   "lines": [
    "forest."
   ]
  }, 
  {
   "begin": "8.240", 
   "end": "8.400", 
   "id": "f000017", 
   "language": "en", 
   "lines": [
    "The"
   ]
  }, 
  {
   "begin": "8.400", 
   "end": "8.880", 
   "id": "f000018", 
   "language": "en", 
   "lines": [
    "Teaks"
   ]
  }, 
  {
   "begin": "8.880", 
   "end": "9.320", 
   "id": "f000019", 
   "language": "en", 
   "lines": [
    "stood"
   ]
  }, 
  {
   "begin": "9.320", 
   "end": "9.840", 
   "id": "f000020", 
   "language": "en", 
   "lines": [
    "tall"
   ]
  }, 
  {
   "begin": "9.840", 
   "end": "10.120", 
   "id": "f000021", 
   "language": "en", 
   "lines": [
    "and"
   ]
  }, 
  {
   "begin": "10.120", 
   "end": "10.880", 
   "id": "f000022", 
   "language": "en", 
   "lines": [
    "erect"
   ]
  }, 
  {
   "begin": "10.880", 
   "end": "11.080", 
   "id": "f000023", 
   "language": "en", 
   "lines": [
    "like"
   ]
  }, 
  {
   "begin": "11.080", 
   "end": "11.840", 
   "id": "f000024", 
   "language": "en", 
   "lines": [
    "soldiers"
   ]
  }, 
  {
   "begin": "11.840", 
   "end": "12.000", 
   "id": "f000025", 
   "language": "en", 
   "lines": [
    "at"
   ]
  }, 
  {
   "begin": "12.000", 
   "end": "12.600", 
   "id": "f000026", 
   "language": "en", 
   "lines": [
    "parade.\n"
   ]
  }, 
  {
   "begin": "12.600", 
   "end": "12.600", 
   "id": "f000027", 
   "language": "en", 
   "lines": [
    ""
   ]
  }, 
  {
   "begin": "12.600", 
   "end": "13.840", 
   "id": "f000028", 
   "language": "en", 
   "lines": [
    "\"Why"
   ]
  }, 
  {
   "begin": "13.840", 
   "end": "14.040", 
   "id": "f000029", 
   "language": "en", 
   "lines": [
    "have"
   ]
  }, 
  {
   "begin": "14.040", 
   "end": "14.160", 
   "id": "f000030", 
   "language": "en", 
   "lines": [
    "you"
   ]
  }, 
  {
   "begin": "14.160", 
   "end": "14.440", 
   "id": "f000031", 
   "language": "en", 
   "lines": [
    "come"
   ]
  }, 
  {
   "begin": "14.440", 
   "end": "15.400", 
   "id": "f000032", 
   "language": "en", 
   "lines": [
    "here?\""
   ]
  }, 
  {
   "begin": "15.400", 
   "end": "15.880", 
   "id": "f000033", 
   "language": "en", 
   "lines": [
    "asked"
   ]
  }, 
  {
   "begin": "15.880", 
   "end": "16.400", 
   "id": "f000034", 
   "language": "en", 
   "lines": [
    "another.\n"
   ]
  }, 
  {
   "begin": "16.400", 
   "end": "16.400", 
   "id": "f000035", 
   "language": "en", 
   "lines": [
    ""
   ]
  }, 
  {
   "begin": "16.400", 
   "end": "17.880", 
   "id": "f000036", 
   "language": "en", 
   "lines": [
    "\"Son,"
   ]
  }, 
  {
   "begin": "17.880", 
   "end": "18.200", 
   "id": "f000037", 
   "language": "en", 
   "lines": [
    "don't"
   ]
  }, 
  {
   "begin": "18.200", 
   "end": "18.520", 
   "id": "f000038", 
   "language": "en", 
   "lines": [
    "you"
   ]
  }, 
  {
   "begin": "18.520", 
   "end": "18.720", 
   "id": "f000039", 
   "language": "en", 
   "lines": [
    "know"
   ]
  }, 
  {
   "begin": "18.720", 
   "end": "18.760", 
   "id": "f000040", 
   "language": "en", 
   "lines": [
    "that"
   ]
  }, 
  {
   "begin": "18.760", 
   "end": "19.080", 
   "id": "f000041", 
   "language": "en", 
   "lines": [
    "this"
   ]
  }, 
  {
   "begin": "19.080", 
   "end": "19.560", 
   "id": "f000042", 
   "language": "en", 
   "lines": [
    "area"
   ]
  }, 
  {
   "begin": "19.560", 
   "end": "19.760", 
   "id": "f000043", 
   "language": "en", 
   "lines": [
    "is"
   ]
  }, 
  {
   "begin": "19.760", 
   "end": "20.280", 
   "id": "f000044", 
   "language": "en", 
   "lines": [
    "reserved"
   ]
  }, 
  {
   "begin": "20.280", 
   "end": "20.440", 
   "id": "f000045", 
   "language": "en", 
   "lines": [
    "for"
   ]
  }, 
  {
   "begin": "20.440", 
   "end": "21.440", 
   "id": "f000046", 
   "language": "en", 
   "lines": [
    "Teak."
   ]
  }, 
  {
   "begin": "21.440", 
   "end": "21.640", 
   "id": "f000047", 
   "language": "en", 
   "lines": [
    "You'd"
   ]
  }, 
  {
   "begin": "21.640", 
   "end": "21.920", 
   "id": "f000048", 
   "language": "en", 
   "lines": [
    "better"
   ]
  }, 
  {
   "begin": "21.920", 
   "end": "22.960", 
   "id": "f000049", 
   "language": "en", 
   "lines": [
    "leave,\""
   ]
  }, 
  {
   "begin": "22.960", 
   "end": "23.200", 
   "id": "f000050", 
   "language": "en", 
   "lines": [
    "an"
   ]
  }, 
  {
   "begin": "23.200", 
   "end": "23.560", 
   "id": "f000051", 
   "language": "en", 
   "lines": [
    "old"
   ]
  }, 
  {
   "begin": "23.560", 
   "end": "24.040", 
   "id": "f000052", 
   "language": "en", 
   "lines": [
    "Teak"
   ]
  }, 
  {
   "begin": "24.040", 
   "end": "25.400", 
   "id": "f000053", 
   "language": "en", 
   "lines": [
    "advised."
   ]
  }, 
  {
   "begin": "25.400", 
   "end": "25.920", 
   "id": "f000054", 
   "language": "en", 
   "lines": [
    "Mango"
   ]
  }, 
  {
   "begin": "25.920", 
   "end": "26.400", 
   "id": "f000055", 
   "language": "en", 
   "lines": [
    "decided"
   ]
  }, 
  {
   "begin": "26.400", 
   "end": "26.600", 
   "id": "f000056", 
   "language": "en", 
   "lines": [
    "to"
   ]
  }, 
  {
   "begin": "26.600", 
   "end": "26.800", 
   "id": "f000057", 
   "language": "en", 
   "lines": [
    "leave"
   ]
  }, 
  {
   "begin": "26.800", 
   "end": "26.960", 
   "id": "f000058", 
   "language": "en", 
   "lines": [
    "the"
   ]
  }, 
  {
   "begin": "26.960", 
   "end": "28.240", 
   "id": "f000059", 
   "language": "en", 
   "lines": [
    "forest."
   ]
  }, 
  {
   "begin": "28.240", 
   "end": "28.400", 
   "id": "f000060", 
   "language": "en", 
   "lines": [
    "He"
   ]
  }, 
  {
   "begin": "28.400", 
   "end": "28.880", 
   "id": "f000061", 
   "language": "en", 
   "lines": [
    "walked"
   ]
  }, 
  {
   "begin": "28.880", 
   "end": "29.320", 
   "id": "f000062", 
   "language": "en", 
   "lines": [
    "on"
   ]
  }, 
  {
   "begin": "29.320", 
   "end": "29.600", 
   "id": "f000063", 
   "language": "en", 
   "lines": [
    "and"
   ]
  }, 
  {
   "begin": "29.600", 
   "end": "30.320", 
   "id": "f000064", 
   "language": "en", 
   "lines": [
    "on"
   ]
  }, 
  {
   "begin": "30.320", 
   "end": "30.440", 
   "id": "f000065", 
   "language": "en", 
   "lines": [
    "but"
   ]
  }, 
  {
   "begin": "30.440", 
   "end": "30.880", 
   "id": "f000066", 
   "language": "en", 
   "lines": [
    "couldn't"
   ]
  }, 
  {
   "begin": "30.880", 
   "end": "31.400", 
   "id": "f000067", 
   "language": "en", 
   "lines": [
    "find"
   ]
  }, 
  {
   "begin": "31.400", 
   "end": "31.800", 
   "id": "f000068", 
   "language": "en", 
   "lines": [
    "water"
   ]
  }, 
  {
   "begin": "31.800", 
   "end": "33.120", 
   "id": "f000069", 
   "language": "en", 
   "lines": [
    "anywhere."
   ]
  }, 
  {
   "begin": "33.120", 
   "end": "33.120", 
   "id": "f000070", 
   "language": "en", 
   "lines": [
    "He"
   ]
  }, 
  {
   "begin": "33.120", 
   "end": "33.520", 
   "id": "f000071", 
   "language": "en", 
   "lines": [
    "thought"
   ]
  }, 
  {
   "begin": "33.520", 
   "end": "33.720", 
   "id": "f000072", 
   "language": "en", 
   "lines": [
    "he"
   ]
  }, 
  {
   "begin": "33.720", 
   "end": "33.920", 
   "id": "f000073", 
   "language": "en", 
   "lines": [
    "would"
   ]
  }, 
  {
   "begin": "33.920", 
   "end": "34.240", 
   "id": "f000074", 
   "language": "en", 
   "lines": [
    "die"
   ]
  }, 
  {
   "begin": "34.240", 
   "end": "34.480", 
   "id": "f000075", 
   "language": "en", 
   "lines": [
    "of"
   ]
  }, 
  {
   "begin": "34.480", 
   "end": "35.000", 
   "id": "f000076", 
   "language": "en", 
   "lines": [
    "thirst.\n"
   ]
  }, 
  {
   "begin": "35.000", 
   "end": "35.760", 
   "id": "f000077", 
   "language": "en", 
   "lines": [
    "He"
   ]
  }, 
  {
   "begin": "35.760", 
   "end": "36.120", 
   "id": "f000078", 
   "language": "en", 
   "lines": [
    "came"
   ]
  }, 
  {
   "begin": "36.120", 
   "end": "36.560", 
   "id": "f000079", 
   "language": "en", 
   "lines": [
    "across"
   ]
  }, 
  {
   "begin": "36.560", 
   "end": "36.640", 
   "id": "f000080", 
   "language": "en", 
   "lines": [
    "an"
   ]
  }, 
  {
   "begin": "36.640", 
   "end": "36.920", 
   "id": "f000081", 
   "language": "en", 
   "lines": [
    "old"
   ]
  }, 
  {
   "begin": "36.920", 
   "end": "37.280", 
   "id": "f000082", 
   "language": "en", 
   "lines": [
    "Fig"
   ]
  }, 
  {
   "begin": "37.280", 
   "end": "37.720", 
   "id": "f000083", 
   "language": "en", 
   "lines": [
    "tree."
   ]
  }, 
  {
   "begin": "37.720", 
   "end": "39.680", 
   "id": "f000084", 
   "language": "en", 
   "lines": [
    "\"Grandpa,"
   ]
  }, 
  {
   "begin": "39.680", 
   "end": "39.920", 
   "id": "f000085", 
   "language": "en", 
   "lines": [
    "where"
   ]
  }, 
  {
   "begin": "39.920", 
   "end": "40.120", 
   "id": "f000086", 
   "language": "en", 
   "lines": [
    "can"
   ]
  }, 
  {
   "begin": "40.120", 
   "end": "40.280", 
   "id": "f000087", 
   "language": "en", 
   "lines": [
    "I"
   ]
  }, 
  {
   "begin": "40.280", 
   "end": "40.560", 
   "id": "f000088", 
   "language": "en", 
   "lines": [
    "get"
   ]
  }, 
  {
   "begin": "40.560", 
   "end": "40.880", 
   "id": "f000089", 
   "language": "en", 
   "lines": [
    "water"
   ]
  }, 
  {
   "begin": "40.880", 
   "end": "41.080", 
   "id": "f000090", 
   "language": "en", 
   "lines": [
    "to"
   ]
  }, 
  {
   "begin": "41.080", 
   "end": "42.080", 
   "id": "f000091", 
   "language": "en", 
   "lines": [
    "drink?\""
   ]
  }, 
  {
   "begin": "42.080", 
   "end": "42.280", 
   "id": "f000092", 
   "language": "en", 
   "lines": [
    "he"
   ]
  }, 
  {
   "begin": "42.280", 
   "end": "42.800", 
   "id": "f000093", 
   "language": "en", 
   "lines": [
    "asked.\n"
   ]
  }, 
  {
   "begin": "42.800", 
   "end": "44.040", 
   "id": "f000094", 
   "language": "en", 
   "lines": [
    "\"What"
   ]
  }, 
  {
   "begin": "44.040", 
   "end": "44.160", 
   "id": "f000095", 
   "language": "en", 
   "lines": [
    "a"
   ]
  }, 
  {
   "begin": "44.160", 
   "end": "44.600", 
   "id": "f000096", 
   "language": "en", 
   "lines": [
    "silly"
   ]
  }, 
  {
   "begin": "44.600", 
   "end": "45.720", 
   "id": "f000097", 
   "language": "en", 
   "lines": [
    "question!"
   ]
  }, 
  {
   "begin": "45.720", 
   "end": "46.160", 
   "id": "f000098", 
   "language": "en", 
   "lines": [
    "You're"
   ]
  }, 
  {
   "begin": "46.160", 
   "end": "46.160", 
   "id": "f000099", 
   "language": "en", 
   "lines": [
    "a"
   ]
  }, 
  {
   "begin": "46.160", 
   "end": "46.880", 
   "id": "f000100", 
   "language": "en", 
   "lines": [
    "tree,"
   ]
  }, 
  {
   "begin": "46.880", 
   "end": "47.400", 
   "id": "f000101", 
   "language": "en", 
   "lines": [
    "aren't"
   ]
  }, 
  {
   "begin": "47.400", 
   "end": "47.680", 
   "id": "f000102", 
   "language": "en", 
   "lines": [
    "you?"
   ]
  }, 
  {
   "begin": "47.680", 
   "end": "48.800", 
   "id": "f000103", 
   "language": "en", 
   "lines": [
    "Push"
   ]
  }, 
  {
   "begin": "48.800", 
   "end": "49.080", 
   "id": "f000104", 
   "language": "en", 
   "lines": [
    "your"
   ]
  }, 
  {
   "begin": "49.080", 
   "end": "49.400", 
   "id": "f000105", 
   "language": "en", 
   "lines": [
    "feet"
   ]
  }, 
  {
   "begin": "49.400", 
   "end": "49.560", 
   "id": "f000106", 
   "language": "en", 
   "lines": [
    "deep"
   ]
  }, 
  {
   "begin": "49.560", 
   "end": "49.680", 
   "id": "f000107", 
   "language": "en", 
   "lines": [
    "into"
   ]
  }, 
  {
   "begin": "49.680", 
   "end": "49.880", 
   "id": "f000108", 
   "language": "en", 
   "lines": [
    "the"
   ]
  }, 
  {
   "begin": "49.880", 
   "end": "50.720", 
   "id": "f000109", 
   "language": "en", 
   "lines": [
    "ground."
   ]
  }, 
  {
   "begin": "50.720", 
   "end": "50.960", 
   "id": "f000110", 
   "language": "en", 
   "lines": [
    "You'll"
   ]
  }, 
  {
   "begin": "50.960", 
   "end": "51.240", 
   "id": "f000111", 
   "language": "en", 
   "lines": [
    "get"
   ]
  }, 
  {
   "begin": "51.240", 
   "end": "52.560", 
   "id": "f000112", 
   "language": "en", 
   "lines": [
    "water."
   ]
  }, 
  {
   "begin": "52.560", 
   "end": "52.680", 
   "id": "f000113", 
   "language": "en", 
   "lines": [
    "You"
   ]
  }, 
  {
   "begin": "52.680", 
   "end": "52.960", 
   "id": "f000114", 
   "language": "en", 
   "lines": [
    "don't"
   ]
  }, 
  {
   "begin": "52.960", 
   "end": "53.160", 
   "id": "f000115", 
   "language": "en", 
   "lines": [
    "need"
   ]
  }, 
  {
   "begin": "53.160", 
   "end": "53.200", 
   "id": "f000116", 
   "language": "en", 
   "lines": [
    "to"
   ]
  }, 
  {
   "begin": "53.200", 
   "end": "53.680", 
   "id": "f000117", 
   "language": "en", 
   "lines": [
    "go"
   ]
  }, 
  {
   "begin": "53.680", 
   "end": "54.360", 
   "id": "f000118", 
   "language": "en", 
   "lines": [
    "anywhere.\"\n"
   ]
  }, 
  {
   "begin": "54.360", 
   "end": "55.120", 
   "id": "f000119", 
   "language": "en", 
   "lines": [
    "\"But"
   ]
  }, 
  {
   "begin": "55.120", 
   "end": "55.480", 
   "id": "f000120", 
   "language": "en", 
   "lines": [
    "that'll"
   ]
  }, 
  {
   "begin": "55.480", 
   "end": "55.720", 
   "id": "f000121", 
   "language": "en", 
   "lines": [
    "take"
   ]
  }, 
  {
   "begin": "55.720", 
   "end": "57.000", 
   "id": "f000122", 
   "language": "en", 
   "lines": [
    "time."
   ]
  }, 
  {
   "begin": "57.000", 
   "end": "57.240", 
   "id": "f000123", 
   "language": "en", 
   "lines": [
    "Isn't"
   ]
  }, 
  {
   "begin": "57.240", 
   "end": "57.720", 
   "id": "f000124", 
   "language": "en", 
   "lines": [
    "there"
   ]
  }, 
  {
   "begin": "57.720", 
   "end": "57.840", 
   "id": "f000125", 
   "language": "en", 
   "lines": [
    "a"
   ]
  }, 
  {
   "begin": "57.840", 
   "end": "58.240", 
   "id": "f000126", 
   "language": "en", 
   "lines": [
    "river"
   ]
  }, 
  {
   "begin": "58.240", 
   "end": "58.600", 
   "id": "f000127", 
   "language": "en", 
   "lines": [
    "nearby?\"\n"
   ]
  }, 
  {
   "begin": "58.600", 
   "end": "60.680", 
   "id": "f000128", 
   "language": "en", 
   "lines": [
    "\"River?"
   ]
  }, 
  {
   "begin": "60.680", 
   "end": "61.000", 
   "id": "f000129", 
   "language": "en", 
   "lines": [
    "What's"
   ]
  }, 
  {
   "begin": "61.000", 
   "end": "61.520", 
   "id": "f000130", 
   "language": "en", 
   "lines": [
    "that?\"\n"
   ]
  }, 
  {
   "begin": "61.520", 
   "end": "62.600", 
   "id": "f000131", 
   "language": "en", 
   "lines": [
    "\"It's"
   ]
  }, 
  {
   "begin": "62.600", 
   "end": "62.840", 
   "id": "f000132", 
   "language": "en", 
   "lines": [
    "water"
   ]
  }, 
  {
   "begin": "62.840", 
   "end": "63.120", 
   "id": "f000133", 
   "language": "en", 
   "lines": [
    "that"
   ]
  }, 
  {
   "begin": "63.120", 
   "end": "63.800", 
   "id": "f000134", 
   "language": "en", 
   "lines": [
    "flows.\"\n"
   ]
  }, 
  {
   "begin": "63.800", 
   "end": "65.480", 
   "id": "f000135", 
   "language": "en", 
   "lines": [
    "\"Oh!"
   ]
  }, 
  {
   "begin": "65.480", 
   "end": "65.600", 
   "id": "f000136", 
   "language": "en", 
   "lines": [
    "Then"
   ]
  }, 
  {
   "begin": "65.600", 
   "end": "66.000", 
   "id": "f000137", 
   "language": "en", 
   "lines": [
    "you'll"
   ]
  }, 
  {
   "begin": "66.000", 
   "end": "66.160", 
   "id": "f000138", 
   "language": "en", 
   "lines": [
    "have"
   ]
  }, 
  {
   "begin": "66.160", 
   "end": "66.360", 
   "id": "f000139", 
   "language": "en", 
   "lines": [
    "to"
   ]
  }, 
  {
   "begin": "66.360", 
   "end": "66.600", 
   "id": "f000140", 
   "language": "en", 
   "lines": [
    "wait"
   ]
  }, 
  {
   "begin": "66.600", 
   "end": "66.920", 
   "id": "f000141", 
   "language": "en", 
   "lines": [
    "till"
   ]
  }, 
  {
   "begin": "66.920", 
   "end": "67.040", 
   "id": "f000142", 
   "language": "en", 
   "lines": [
    "it"
   ]
  }, 
  {
   "begin": "67.040", 
   "end": "68.360", 
   "id": "f000143", 
   "language": "en", 
   "lines": [
    "rains.\"\n"
   ]
  }, 
  {
   "begin": "68.360", 
   "end": "68.760", 
   "id": "f000144", 
   "language": "en", 
   "lines": [
    "Mango"
   ]
  }, 
  {
   "begin": "68.760", 
   "end": "69.000", 
   "id": "f000145", 
   "language": "en", 
   "lines": [
    "left"
   ]
  }, 
  {
   "begin": "69.000", 
   "end": "69.680", 
   "id": "f000146", 
   "language": "en", 
   "lines": [
    "him"
   ]
  }, 
  {
   "begin": "69.680", 
   "end": "69.880", 
   "id": "f000147", 
   "language": "en", 
   "lines": [
    "and"
   ]
  }, 
  {
   "begin": "69.880", 
   "end": "70.240", 
   "id": "f000148", 
   "language": "en", 
   "lines": [
    "walked"
   ]
  }, 
  {
   "begin": "70.240", 
   "end": "70.520", 
   "id": "f000149", 
   "language": "en", 
   "lines": [
    "on"
   ]
  }, 
  {
   "begin": "70.520", 
   "end": "70.760", 
   "id": "f000150", 
   "language": "en", 
   "lines": [
    "through"
   ]
  }, 
  {
   "begin": "70.760", 
   "end": "71.000", 
   "id": "f000151", 
   "language": "en", 
   "lines": [
    "the"
   ]
  }, 
  {
   "begin": "71.000", 
   "end": "72.080", 
   "id": "f000152", 
   "language": "en", 
   "lines": [
    "mist."
   ]
  }, 
  {
   "begin": "72.080", 
   "end": "72.320", 
   "id": "f000153", 
   "language": "en", 
   "lines": [
    "Giddy"
   ]
  }, 
  {
   "begin": "72.320", 
   "end": "72.560", 
   "id": "f000154", 
   "language": "en", 
   "lines": [
    "with"
   ]
  }, 
  {
   "begin": "72.560", 
   "end": "73.200", 
   "id": "f000155", 
   "language": "en", 
   "lines": [
    "hunger"
   ]
  }, 
  {
   "begin": "73.200", 
   "end": "73.560", 
   "id": "f000156", 
   "language": "en", 
   "lines": [
    "and"
   ]
  }, 
  {
   "begin": "73.560", 
   "end": "73.640", 
   "id": "f000157", 
   "language": "en", 
   "lines": [
    "thirst,"
   ]
  }, 
  {
   "begin": "73.640", 
   "end": "74.200", 
   "id": "f000158", 
   "language": "en", 
   "lines": [
    "he"
   ]
  }, 
  {
   "begin": "74.200", 
   "end": "74.720", 
   "id": "f000159", 
   "language": "en", 
   "lines": [
    "stumbled"
   ]
  }, 
  {
   "begin": "74.720", 
   "end": "75.120", 
   "id": "f000160", 
   "language": "en", 
   "lines": [
    "against"
   ]
  }, 
  {
   "begin": "75.120", 
   "end": "75.600", 
   "id": "f000161", 
   "language": "en", 
   "lines": [
    "stones,"
   ]
  }, 
  {
   "begin": "75.600", 
   "end": "76.280", 
   "id": "f000162", 
   "language": "en", 
   "lines": [
    "bumped"
   ]
  }, 
  {
   "begin": "76.280", 
   "end": "76.560", 
   "id": "f000163", 
   "language": "en", 
   "lines": [
    "into"
   ]
  }, 
  {
   "begin": "76.560", 
   "end": "76.880", 
   "id": "f000164", 
   "language": "en", 
   "lines": [
    "other"
   ]
  }, 
  {
   "begin": "76.880", 
   "end": "77.960", 
   "id": "f000165", 
   "language": "en", 
   "lines": [
    "trees."
   ]
  }, 
  {
   "begin": "77.960", 
   "end": "78.160", 
   "id": "f000166", 
   "language": "en", 
   "lines": [
    "They"
   ]
  }, 
  {
   "begin": "78.160", 
   "end": "78.800", 
   "id": "f000167", 
   "language": "en", 
   "lines": [
    "cursed,"
   ]
  }, 
  {
   "begin": "78.800", 
   "end": "79.880", 
   "id": "f000168", 
   "language": "en", 
   "lines": [
    "\"Blind"
   ]
  }, 
  {
   "begin": "79.880", 
   "end": "80.560", 
   "id": "f000169", 
   "language": "en", 
   "lines": [
    "fool!\""
   ]
  }, 
  {
   "begin": "80.560", 
   "end": "81.600", 
   "id": "f000170", 
   "language": "en", 
   "lines": [
    "\"Clumsy"
   ]
  }, 
  {
   "begin": "81.600", 
   "end": "82.080", 
   "id": "f000171", 
   "language": "en", 
   "lines": [
    "oaf!\""
   ]
  }, 
  {
   "begin": "82.080", 
   "end": "82.840", 
   "id": "f000172", 
   "language": "en", 
   "lines": [
    "\"I"
   ]
  }, 
  {
   "begin": "82.840", 
   "end": "83.080", 
   "id": "f000173", 
   "language": "en", 
   "lines": [
    "say,"
   ]
  }, 
  {
   "begin": "83.080", 
   "end": "83.440", 
   "id": "f000174", 
   "language": "en", 
   "lines": [
    "look"
   ]
  }, 
  {
   "begin": "83.440", 
   "end": "83.640", 
   "id": "f000175", 
   "language": "en", 
   "lines": [
    "where"
   ]
  }, 
  {
   "begin": "83.640", 
   "end": "84.120", 
   "id": "f000176", 
   "language": "en", 
   "lines": [
    "you're"
   ]
  }, 
  {
   "begin": "84.120", 
   "end": "85.320", 
   "id": "f000177", 
   "language": "en", 
   "lines": [
    "going.\"\n"
   ]
  }, 
  {
   "begin": "85.320", 
   "end": "85.640", 
   "id": "f000178", 
   "language": "en", 
   "lines": [
    "Soon"
   ]
  }, 
  {
   "begin": "85.640", 
   "end": "85.720", 
   "id": "f000179", 
   "language": "en", 
   "lines": [
    "the"
   ]
  }, 
  {
   "begin": "85.720", 
   "end": "86.120", 
   "id": "f000180", 
   "language": "en", 
   "lines": [
    "sun"
   ]
  }, 
  {
   "begin": "86.120", 
   "end": "86.600", 
   "id": "f000181", 
   "language": "en", 
   "lines": [
    "rose"
   ]
  }, 
  {
   "begin": "86.600", 
   "end": "86.760", 
   "id": "f000182", 
   "language": "en", 
   "lines": [
    "and"
   ]
  }, 
  {
   "begin": "86.760", 
   "end": "87.160", 
   "id": "f000183", 
   "language": "en", 
   "lines": [
    "once"
   ]
  }, 
  {
   "begin": "87.160", 
   "end": "87.400", 
   "id": "f000184", 
   "language": "en", 
   "lines": [
    "again"
   ]
  }, 
  {
   "begin": "87.400", 
   "end": "87.520", 
   "id": "f000185", 
   "language": "en", 
   "lines": [
    "the"
   ]
  }, 
  {
   "begin": "87.520", 
   "end": "87.920", 
   "id": "f000186", 
   "language": "en", 
   "lines": [
    "path"
   ]
  }, 
  {
   "begin": "87.920", 
   "end": "88.160", 
   "id": "f000187", 
   "language": "en", 
   "lines": [
    "was"
   ]
  }, 
  {
   "begin": "88.160", 
   "end": "88.640", 
   "id": "f000188", 
   "language": "en", 
   "lines": [
    "clearly"
   ]
  }, 
  {
   "begin": "88.640", 
   "end": "89.920", 
   "id": "f000189", 
   "language": "en", 
   "lines": [
    "visible."
   ]
  }, 
  {
   "begin": "89.920", 
   "end": "90.160", 
   "id": "f000190", 
   "language": "en", 
   "lines": [
    "Mango"
   ]
  }, 
  {
   "begin": "90.160", 
   "end": "90.480", 
   "id": "f000191", 
   "language": "en", 
   "lines": [
    "was"
   ]
  }, 
  {
   "begin": "90.480", 
   "end": "91.240", 
   "id": "f000192", 
   "language": "en", 
   "lines": [
    "exhausted"
   ]
  }, 
  {
   "begin": "91.240", 
   "end": "91.440", 
   "id": "f000193", 
   "language": "en", 
   "lines": [
    "and"
   ]
  }, 
  {
   "begin": "91.440", 
   "end": "92.040", 
   "id": "f000194", 
   "language": "en", 
   "lines": [
    "sweaty"
   ]
  }, 
  {
   "begin": "92.040", 
   "end": "92.440", 
   "id": "f000195", 
   "language": "en", 
   "lines": [
    "but"
   ]
  }, 
  {
   "begin": "92.440", 
   "end": "92.720", 
   "id": "f000196", 
   "language": "en", 
   "lines": [
    "he"
   ]
  }, 
  {
   "begin": "92.720", 
   "end": "93.080", 
   "id": "f000197", 
   "language": "en", 
   "lines": [
    "walked"
   ]
  }, 
  {
   "begin": "93.080", 
   "end": "93.320", 
   "id": "f000198", 
   "language": "en", 
   "lines": [
    "on"
   ]
  }, 
  {
   "begin": "93.320", 
   "end": "93.640", 
   "id": "f000199", 
   "language": "en", 
   "lines": [
    "past"
   ]
  }, 
  {
   "begin": "93.640", 
   "end": "93.800", 
   "id": "f000200", 
   "language": "en", 
   "lines": [
    "the"
   ]
  }, 
  {
   "begin": "93.800", 
   "end": "94.240", 
   "id": "f000201", 
   "language": "en", 
   "lines": [
    "trees"
   ]
  }, 
  {
   "begin": "94.240", 
   "end": "94.440", 
   "id": "f000202", 
   "language": "en", 
   "lines": [
    "till"
   ]
  }, 
  {
   "begin": "94.440", 
   "end": "95.000", 
   "id": "f000203", 
   "language": "en", 
   "lines": [
    "he"
   ]
  }, 
  {
   "begin": "95.000", 
   "end": "95.280", 
   "id": "f000204", 
   "language": "en", 
   "lines": [
    "reached"
   ]
  }, 
  {
   "begin": "95.280", 
   "end": "95.400", 
   "id": "f000205", 
   "language": "en", 
   "lines": [
    "the"
   ]
  }, 
  {
   "begin": "95.400", 
   "end": "95.480", 
   "id": "f000206", 
   "language": "en", 
   "lines": [
    "top"
   ]
  }, 
  {
   "begin": "95.480", 
   "end": "95.680", 
   "id": "f000207", 
   "language": "en", 
   "lines": [
    "of"
   ]
  }, 
  {
   "begin": "95.680", 
   "end": "95.960", 
   "id": "f000208", 
   "language": "en", 
   "lines": [
    "a"
   ]
  }, 
  {
   "begin": "95.960", 
   "end": "96.880", 
   "id": "f000209", 
   "language": "en", 
   "lines": [
    "hill."
   ]
  }, 
  {
   "begin": "96.880", 
   "end": "97.120", 
   "id": "f000210", 
   "language": "en", 
   "lines": [
    "There"
   ]
  }, 
  {
   "begin": "97.120", 
   "end": "97.520", 
   "id": "f000211", 
   "language": "en", 
   "lines": [
    "he"
   ]
  }, 
  {
   "begin": "97.520", 
   "end": "97.760", 
   "id": "f000212", 
   "language": "en", 
   "lines": [
    "stood,"
   ]
  }, 
  {
   "begin": "97.760", 
   "end": "98.680", 
   "id": "f000213", 
   "language": "en", 
   "lines": [
    "thirsting"
   ]
  }, 
  {
   "begin": "98.680", 
   "end": "98.880", 
   "id": "f000214", 
   "language": "en", 
   "lines": [
    "for"
   ]
  }, 
  {
   "begin": "98.880", 
   "end": "99.640", 
   "id": "f000215", 
   "language": "en", 
   "lines": [
    "water."
   ]
  }
 ]
}