{
 "fragments": [
  {
   "begin": "0.000", 
   "end": "15.680", 
   "id": "f000001", 
   "language": "en", 
   "lines": [
    "\ufeffMango couldn't understand why she put up with it. Tamarind said, \"Let them be They don't bother me all the year round. Anyway, what can I do? I can't run away, can I?\"\n"
   ]
  }, 
  {
   "begin": "15.680", 
   "end": "39.400", 
   "id": "f000002", 
   "language": "en", 
   "lines": [
    "When Mango was in flower for the first time Tamarind said, \"Look out! It will be your turn now!\" She was right. No sooner had Mango's little green fruit begun to turn yellow than the urchins began firing volleys of stones with their catapults. Mango complained, \"I am sore all over. I wish I could run away from here!\"\n"
   ]
  }, 
  {
   "begin": "39.400", 
   "end": "48.960", 
   "id": "f000003", 
   "language": "en", 
   "lines": [
    "Tamarind laughed. \"Run away! Don't be silly. This is our life. We have to live and die here.\"\n"
   ]
  }, 
  {
   "begin": "48.960", 
   "end": "69.440", 
   "id": "f000004", 
   "language": "en", 
   "lines": [
    "Her words set Mango thinking: butterflies spread their wings and fly; lambs frolic in green meadows; clouds glide across the sky; as for men, they move about freely. Why are we trees condemned to stay in one place? What would happen if I started walking?\n"
   ]
  }, 
  {
   "begin": "69.440", 
   "end": "85.080", 
   "id": "f000005", 
   "language": "en", 
   "lines": [
    "He confided his thoughts to his friends but they said, \"It is God's will that we stay in one place. We get all our food without moving, just sitting, or rather, standing. Then why should we wander about?\"\n"
   ]
  }, 
  {
   "begin": "85.080", 
   "end": "89.800", 
   "id": "f000006", 
   "language": "en", 
   "lines": [
    "But he would not agree, so they began calling him \"Mad mango.\""
   ]
  }
 ]
}